{
	"info": {
		"_postman_id": "360155b0-8ea9-42d1-b85e-640a7814d9d6",
		"name": "Mahire Floral",
		"schema": "https://schema.getpostman.com/json/collection/v2.1.0/collection.json"
	},
	"item": [
		{
			"name": "Core",
			"item": []
		},
		{
			"name": "Shop Stocker",
			"item": [
				{
					"name": "Entry Receive Product",
					"request": {
						"method": "PUT",
						"header": [
							{
								"key": "Authorization",
								"type": "text",
								"value": "HLTLyTd79VvZyTY0lYdhITYEOccimQM2gKK2HtDSsR8KppWeYB"
							},
							{
								"key": "Content-Type",
								"name": "Content-Type",
								"type": "text",
								"value": "application/json"
							}
						],
						"body": {
							"mode": "raw",
							"raw": "{\n\t\"shop_stock_id\":4\n}"
						},
						"url": {
							"raw": "http://localhost/core-api/shopstocker/entry_receive_product.php",
							"protocol": "http",
							"host": [
								"localhost"
							],
							"path": [
								"core-api",
								"shopstocker",
								"entry_receive_product.php"
							]
						}
					},
					"response": []
				},
				{
					"name": "Entry Sold Item",
					"request": {
						"method": "POST",
						"header": [
							{
								"key": "Authorization",
								"type": "text",
								"value": "HLTLyTd79VvZyTY0lYdhITYEOccimQM2gKK2HtDSsR8KppWeYB"
							},
							{
								"key": "Content-Type",
								"name": "Content-Type",
								"type": "text",
								"value": "application/json"
							}
						],
						"body": {
							"mode": "raw",
							"raw": ""
						},
						"url": {
							"raw": "http://localhost/core-api/shopstocker/entry_sold_item.php",
							"protocol": "http",
							"host": [
								"localhost"
							],
							"path": [
								"core-api",
								"shopstocker",
								"entry_sold_item.php"
							]
						}
					},
					"response": []
				},
				{
					"name": "Get Sold Item",
					"request": {
						"method": "POST",
						"header": [
							{
								"key": "Authorization",
								"type": "text",
								"value": "HLTLyTd79VvZyTY0lYdhITYEOccimQM2gKK2HtDSsR8KppWeYB",
								"disabled": true
							},
							{
								"key": "Content-Type",
								"name": "Content-Type",
								"type": "text",
								"value": "application/json"
							},
							{
								"key": "Authorization",
								"value": "Wfsu6gLyc9D4qxzvzTdhw7hKvzMx2pcxXrWnIQ9bwDN5HPcuBq",
								"description": "Admin",
								"type": "text"
							}
						],
						"body": {
							"mode": "raw",
							"raw": "{\n\t\"month\":3,\n\t\"year\":2019,\n\t\"filter_by_shop_id\":2\n}"
						},
						"url": {
							"raw": "http://localhost/mahir_floral_api_project/shopstocker/get_sold_item.php",
							"protocol": "http",
							"host": [
								"localhost"
							],
							"path": [
								"mahir_floral_api_project",
								"shopstocker",
								"get_sold_item.php"
							]
						}
					},
					"response": []
				},
				{
					"name": "Get Shop Stocks",
					"request": {
						"method": "POST",
						"header": [
							{
								"key": "Authorization",
								"type": "text",
								"value": "HLTLyTd79VvZyTY0lYdhITYEOccimQM2gKK2HtDSsR8KppWeYB",
								"disabled": true
							},
							{
								"key": "Content-Type",
								"name": "Content-Type",
								"type": "text",
								"value": "application/json"
							},
							{
								"key": "Authorization",
								"value": "6c6lkgaK0X6lePlCx1y4SeUObJUmY1q4xwIRRz1YvDSUApi66K",
								"description": "admin",
								"type": "text"
							},
							{
								"key": "Authorization",
								"value": "GdZy066DHdli4Xl8HUkxL3VdOhif7KewYx6oNpXVu6yeueEXiP",
								"description": "Not Owner",
								"type": "text",
								"disabled": true
							}
						],
						"body": {
							"mode": "raw",
							"raw": "{\n\t\"month\":4,\n\t\"year\":2019,\n\t\"filter_by_shop_id\": 2\n}\n"
						},
						"url": {
							"raw": "http://localhost/mahir_floral_api_project/shopstocker/get_shop_stock.php",
							"protocol": "http",
							"host": [
								"localhost"
							],
							"path": [
								"mahir_floral_api_project",
								"shopstocker",
								"get_shop_stock.php"
							]
						}
					},
					"response": []
				}
			]
		},
		{
			"name": "Raw Stock",
			"item": [
				{
					"name": "Get Delivered Stocks",
					"request": {
						"method": "POST",
						"header": [
							{
								"key": "Authorization",
								"type": "text",
								"value": "vuQ9YCXjjpr51v0GeQ28rGyNRdDn6iJT9ucimk2XCXYn1M3g0V"
							},
							{
								"key": "Content-Type",
								"name": "Content-Type",
								"type": "text",
								"value": "application/json"
							}
						],
						"body": {
							"mode": "raw",
							"raw": "{\n\t\"month\":\"04\",\n\t\"year\":2019\n}\n"
						},
						"url": {
							"raw": "http://localhost/mahir_floral_api_project/rawstocker/get_delivered_stock.php",
							"protocol": "http",
							"host": [
								"localhost"
							],
							"path": [
								"mahir_floral_api_project",
								"rawstocker",
								"get_delivered_stock.php"
							]
						}
					},
					"response": []
				},
				{
					"name": "Entry Raw Stock",
					"request": {
						"method": "POST",
						"header": [
							{
								"key": "Authorization",
								"type": "text",
								"value": "IpLdt5uMVWkTiJPdsC1BrOG4Me7uWq1mtRyHh5WWqtBoiMtaRv"
							},
							{
								"key": "Content-Type",
								"name": "Content-Type",
								"type": "text",
								"value": "application/json"
							}
						],
						"body": {
							"mode": "raw",
							"raw": "{\n\t\"product_name\":\"Rose\",\n\t\"quantity\":8,\n\t\"unit\":\"Pieces\",\n\t\"color\": \"Red\",\n\t\"comment\": \"No Comment at all\"\n}"
						},
						"url": {
							"raw": "https://mahirfloralevents.com/mahir_floral_api_project/rawstocker/entry_raw_stock.php",
							"protocol": "https",
							"host": [
								"mahirfloralevents",
								"com"
							],
							"path": [
								"mahir_floral_api_project",
								"rawstocker",
								"entry_raw_stock.php"
							]
						}
					},
					"response": []
				},
				{
					"name": "Entry Deliver Product",
					"request": {
						"method": "POST",
						"header": [
							{
								"key": "Authorization",
								"type": "text",
								"value": "KFkaQwav24nviLKHlhHHt9lp0Bm9ZxTBkBBP00eQFF7gu8AQ8R"
							},
							{
								"key": "Content-Type",
								"name": "Content-Type",
								"type": "text",
								"value": "application/json"
							}
						],
						"body": {
							"mode": "raw",
							"raw": "{\n\t\"shop_id\":\"6\",\n\t\"product_id\":2,\n\t\"quantity\":2,\n\t\"comment\": \"test delivery\"\n}"
						},
						"url": {
							"raw": "http://localhost/mahir_floral_api_project/rawstocker/entry_deliver_product.php",
							"protocol": "http",
							"host": [
								"localhost"
							],
							"path": [
								"mahir_floral_api_project",
								"rawstocker",
								"entry_deliver_product.php"
							]
						}
					},
					"response": []
				},
				{
					"name": "Get raw stocks",
					"request": {
						"method": "POST",
						"header": [
							{
								"key": "Authorization",
								"type": "text",
								"value": "HLTLyTd79VvZyTY0lYdhITYEOccimQM2gKK2HtDSsR8KppWeYB",
								"disabled": true
							},
							{
								"key": "Content-Type",
								"name": "Content-Type",
								"value": "application/json",
								"type": "text"
							},
							{
								"key": "Authorization",
								"value": "IpLdt5uMVWkTiJPdsC1BrOG4Me7uWq1mtRyHh5WWqtBoiMtaRv",
								"type": "text"
							},
							{
								"key": "",
								"value": "jBUVO7Q9E5sCie6qGlKvamx5o2Aj23jLsFuJLkpTJVlHzjO3Yv",
								"type": "text",
								"disabled": true
							}
						],
						"body": {
							"mode": "raw",
							"raw": "\r\n{\r\n\t\"month\":4,\r\n\t\"year\":2019\r\n}\r\n"
						},
						"url": {
							"raw": "https://mahirfloralevents.com/mahir_floral_api_project/rawstocker/get_raw_stock.php",
							"protocol": "https",
							"host": [
								"mahirfloralevents",
								"com"
							],
							"path": [
								"mahir_floral_api_project",
								"rawstocker",
								"get_raw_stock.php"
							]
						}
					},
					"response": []
				},
				{
					"name": "Entry Ready Stock",
					"request": {
						"method": "POST",
						"header": [
							{
								"key": "Authorization",
								"type": "text",
								"value": "KFkaQwav24nviLKHlhHHt9lp0Bm9ZxTBkBBP00eQFF7gu8AQ8R"
							},
							{
								"key": "Content-Type",
								"name": "Content-Type",
								"type": "text",
								"value": "application/json"
							}
						],
						"body": {
							"mode": "raw",
							"raw": "{\n\t\"product_name\":\"Rose with Tulip\",\n\t\"quantity\":4,\n\t\"price\":120,\n\t\"unit\":\"Boxs\",\n\t\"color\": \"REd\",\n\t\"comment\": \"No comment for now\"\n}"
						},
						"url": {
							"raw": "http://localhost/mahir_floral_api_project/rawstocker/entry_ready_stock.php",
							"protocol": "http",
							"host": [
								"localhost"
							],
							"path": [
								"mahir_floral_api_project",
								"rawstocker",
								"entry_ready_stock.php"
							]
						}
					},
					"response": []
				},
				{
					"name": "Get Ready Stock",
					"request": {
						"method": "POST",
						"header": [
							{
								"key": "Authorization",
								"type": "text",
								"value": "KFkaQwav24nviLKHlhHHt9lp0Bm9ZxTBkBBP00eQFF7gu8AQ8R"
							},
							{
								"key": "Content-Type",
								"name": "Content-Type",
								"type": "text",
								"value": "application/json"
							},
							{
								"key": "Authorization",
								"value": "xF2i9czSgSm6xjD6Y15tH9mXNy9YNJc4a5r1VruxstYcvWzJgH",
								"description": "admin",
								"type": "text",
								"disabled": true
							},
							{
								"key": "Authorization",
								"value": "wuWE0KLOwmg9s3VEQH804j9Fb9OE81M7eHflQ4NugTGFIznVFr",
								"type": "text",
								"disabled": true
							}
						],
						"body": {
							"mode": "raw",
							"raw": "{\n\t\"month\":\"04\",\n\t\"year\":2019\n}"
						},
						"url": {
							"raw": "http://localhost/mahir_floral_api_project/rawstocker/get_ready_stock.php",
							"protocol": "http",
							"host": [
								"localhost"
							],
							"path": [
								"mahir_floral_api_project",
								"rawstocker",
								"get_ready_stock.php"
							]
						}
					},
					"response": []
				}
			]
		},
		{
			"name": "Staff",
			"item": [
				{
					"name": "Staff Signup",
					"request": {
						"method": "POST",
						"header": [
							{
								"key": "Authorization",
								"value": "eTxVlyzciGZqPE0wCFvuw7t1tNHRaQ2Q9jOUkY1BpZrVjOM1W0",
								"description": "admin",
								"type": "text"
							},
							{
								"key": "Content-Type",
								"name": "Content-Type",
								"value": "application/json",
								"type": "text"
							}
						],
						"body": {
							"mode": "raw",
							"raw": "{\n\t\"email\": \"staff_raw03@gmail.com\",\n    \"password\": \"12345678\",\n    \"name\": \"Devid raw stocker\",\n    \"shop_id\":3,\n    \"role\": \"Raw Stock\"\n}"
						},
						"url": {
							"raw": "http://mahirfloralevents.com/mahir_floral_api_project/admin/staff_registration.php",
							"protocol": "http",
							"host": [
								"mahirfloralevents",
								"com"
							],
							"path": [
								"mahir_floral_api_project",
								"admin",
								"staff_registration.php"
							]
						}
					},
					"response": []
				},
				{
					"name": "Login",
					"request": {
						"method": "POST",
						"header": [
							{
								"key": "Content-Type",
								"name": "Content-Type",
								"value": "application/json",
								"type": "text"
							}
						],
						"body": {
							"mode": "raw",
							"raw": "{\n\t\"email\":\"staff_raw@gmail.com\",\n\t\"password\":\"12345678\"\n}"
						},
						"url": {
							"raw": "http://localhost/mahir_floral_api_project/staff/Login.php?",
							"protocol": "http",
							"host": [
								"localhost"
							],
							"path": [
								"mahir_floral_api_project",
								"staff",
								"Login.php"
							],
							"query": [
								{
									"key": "email",
									"value": "staff_raw@gmail.com",
									"disabled": true
								},
								{
									"key": "password",
									"value": "12345678",
									"disabled": true
								}
							]
						}
					},
					"response": []
				},
				{
					"name": "User Info",
					"request": {
						"method": "POST",
						"header": [
							{
								"key": "Content-Type",
								"name": "Content-Type",
								"type": "text",
								"value": "application/json"
							},
							{
								"key": "Authorization",
								"value": "ja2nZtcx2BFjDUDMCxh2KTH8pgBf22RI1RG33xmpjNiGN5e07c",
								"type": "text"
							}
						],
						"body": {
							"mode": "raw",
							"raw": ""
						},
						"url": {
							"raw": "http://localhost/mahir_floral_api_project/staff/get_user_info.php",
							"protocol": "http",
							"host": [
								"localhost"
							],
							"path": [
								"mahir_floral_api_project",
								"staff",
								"get_user_info.php"
							]
						}
					},
					"response": []
				}
			]
		},
		{
			"name": "Shop",
			"item": [
				{
					"name": "Shop Registration",
					"request": {
						"method": "POST",
						"header": [
							{
								"key": "Authorization",
								"type": "text",
								"value": "w2WwEDpZD2MGsewvEO7UdroSPCTc0PZHAswROk8tvMgAYpD0Y3"
							},
							{
								"key": "Content-Type",
								"name": "Content-Type",
								"type": "text",
								"value": "application/json"
							}
						],
						"body": {
							"mode": "raw",
							"raw": "{\n\t\"shop_name\":\"HQ\",\n\t\"location\":\"ariston newyork, 1992\",\n\t\"latitude\":\"24.28181\",\n\t\"longitude\": \"91.33411\"\n}"
						},
						"url": {
							"raw": "http://localhost/mahir_floral_api_project/admin/shop_registration.php",
							"protocol": "http",
							"host": [
								"localhost"
							],
							"path": [
								"mahir_floral_api_project",
								"admin",
								"shop_registration.php"
							]
						}
					},
					"response": []
				},
				{
					"name": "Get Shops",
					"protocolProfileBehavior": {
						"disableBodyPruning": true
					},
					"request": {
						"method": "GET",
						"header": [
							{
								"key": "Authorization",
								"type": "text",
								"value": "mEs9HIQRhcDq9336LlXDaE8sQaw1IPMCO01UKWtrLzpeZ8nTNf"
							},
							{
								"key": "Content-Type",
								"name": "Content-Type",
								"type": "text",
								"value": "application/json"
							}
						],
						"body": {
							"mode": "raw",
							"raw": ""
						},
						"url": {
							"raw": "http://localhost/mahir_floral_api_project/admin/getshops.php",
							"protocol": "http",
							"host": [
								"localhost"
							],
							"path": [
								"mahir_floral_api_project",
								"admin",
								"getshops.php"
							]
						}
					},
					"response": []
				}
			]
		},
		{
			"name": "User Online Status",
			"request": {
				"method": "POST",
				"header": [
					{
						"key": "Content-Type",
						"value": "application/json",
						"type": "text"
					}
				],
				"body": {
					"mode": "raw",
					"raw": "{\n\t\"user_id\":4\n}"
				},
				"url": {
					"raw": "https://mahirfloralevents.com/mahir_floral_api_project/staff/get_user_online_status.php",
					"protocol": "https",
					"host": [
						"mahirfloralevents",
						"com"
					],
					"path": [
						"mahir_floral_api_project",
						"staff",
						"get_user_online_status.php"
					],
					"query": [
						{
							"key": "user_id",
							"value": "4",
							"disabled": true
						}
					]
				}
			},
			"response": [
				{
					"name": "User Online Status",
					"originalRequest": {
						"method": "POST",
						"header": [
							{
								"key": "Authorization",
								"type": "text",
								"value": "xF2i9czSgSm6xjD6Y15tH9mXNy9YNJc4a5r1VruxstYcvWzJgH",
								"disabled": true
							},
							{
								"key": "Content-Type",
								"name": "Content-Type",
								"type": "text",
								"value": "application/json"
							}
						],
						"body": {
							"mode": "raw",
							"raw": "{\n\t\"user_id\":1\n}"
						},
						"url": {
							"raw": "http://localhost/core-api/staff/get_user_online_status.php",
							"protocol": "http",
							"host": [
								"localhost"
							],
							"path": [
								"core-api",
								"staff",
								"get_user_online_status.php"
							]
						}
					},
					"status": "Service Unavailable",
					"code": 503,
					"_postman_previewlanguage": "json",
					"header": [
						{
							"key": "Date",
							"value": "Sat, 23 Mar 2019 17:18:49 GMT"
						},
						{
							"key": "Server",
							"value": "Apache/2.4.37 (Win32) OpenSSL/1.1.1a PHP/7.3.0"
						},
						{
							"key": "X-Powered-By",
							"value": "PHP/7.3.0"
						},
						{
							"key": "Access-Control-Allow-Origin",
							"value": "*"
						},
						{
							"key": "Content-Length",
							"value": "75"
						},
						{
							"key": "Connection",
							"value": "close"
						},
						{
							"key": "Content-Type",
							"value": "application/json; charset=UTF-8"
						}
					],
					"cookie": [],
					"body": "{\n    \"response\": {\n        \"status\": false,\n        \"message\": \"Unable To Signup Please Try Later\"\n    }\n}"
				}
			]
		},
		{
			"name": "User Check",
			"request": {
				"method": "POST",
				"header": [
					{
						"key": "Content-Type",
						"name": "Content-Type",
						"value": "application/json",
						"type": "text"
					}
				],
				"body": {
					"mode": "raw",
					"raw": "{\n\t\"user_id\": \"4\",\n\t\"user_check\": \"0\"\n}"
				},
				"url": {
					"raw": "http://localhost/mahir_floral_api_project/staff/user_check.php",
					"protocol": "http",
					"host": [
						"localhost"
					],
					"path": [
						"mahir_floral_api_project",
						"staff",
						"user_check.php"
					]
				}
			},
			"response": []
		},
		{
			"name": "Timesheet By Week",
			"request": {
				"method": "POST",
				"header": [
					{
						"key": "Content-Type",
						"name": "Content-Type",
						"type": "text",
						"value": "application/json"
					}
				],
				"body": {
					"mode": "raw",
					"raw": "{\n\t\"filter_type\":\"week\",\n\t\"week_num\": \"15\",\n\t\"year\": 2019\n}"
				},
				"url": {
					"raw": "http://mahirfloralevents.com/mahir_floral_api_project/staff/timesheet.php",
					"protocol": "http",
					"host": [
						"mahirfloralevents",
						"com"
					],
					"path": [
						"mahir_floral_api_project",
						"staff",
						"timesheet.php"
					]
				}
			},
			"response": []
		},
		{
			"name": "Timesheet By Date",
			"request": {
				"method": "POST",
				"header": [
					{
						"key": "Content-Type",
						"name": "Content-Type",
						"type": "text",
						"value": "application/json"
					}
				],
				"body": {
					"mode": "raw",
					"raw": "{\n\t\"filter_type\":\"date\",\n\t\"start_date\": \"18/03/2019\",\n\t\"end_date\": \"24/03/2019\"\n}"
				},
				"url": {
					"raw": "http://localhost/core-api/staff/timesheet.php",
					"protocol": "http",
					"host": [
						"localhost"
					],
					"path": [
						"core-api",
						"staff",
						"timesheet.php"
					]
				}
			},
			"response": []
		}
	]
}